<?xml version="1.0" encoding="utf-8" ?><dwsync><file name="0UCSIYgj7u" server="60.43.193.157" local="3562902864" remote="602446763947067632" Dst="-1" /><file name="sess_2fb740fe3a40c67df98e56c288b6ed9f643e3c25" server="60.43.193.157" local="3562902864" remote="-4611698899819049104" Dst="-1" /><file name="sess_618bb53de96b34ed93afb361cb6dcc9e6eb645b1" server="60.43.193.157" local="3562902864" remote="-4611698899819049104" Dst="-1" /><file name="sess_66a81dced11ee438e48a259cd43a12c164424d78" server="60.43.193.157" local="3562902864" remote="-4611698899819049104" Dst="-1" /><file name="sess_a16b5958b71be042420c6bde21ecbaa1b9bf6681" server="60.43.193.157" local="3562902864" remote="-4611698899819049104" Dst="-1" /><file name="sess_aef0a9fece325561aaa9adcad280dbf9ad7feee4" server="60.43.193.157" local="3562902864" remote="-4611698899819049104" Dst="-1" /><file name="sess_be694c5202dea55df66253bc19532c2f16b91feb" server="60.43.193.157" local="3562902864" remote="-4611698899818962704" Dst="-1" /><file name="sess_cdaa1e25b04c0fdc1e1a5f9cf84d1e79e843afa8" server="60.43.193.157" local="3562902864" remote="-4611698899819049104" Dst="-1" /><file name="sess_c9393fa96089c203f098a7dbe4e772bc1ca0999f" server="60.43.193.157" local="3562902864" remote="-4611698899820345104" Dst="-1" /><file name="sess_d7233dcccdf8ccfef5a72c4f2738ee044825fb3d" server="60.43.193.157" local="3562902864" remote="-4611698899819049104" Dst="-1" /><file name="set_jp_profile.pl" server="60.43.193.157" local="3562902864" remote="-4611698899983641104" Dst="-1" /><file name="setup" server="60.43.193.157" local="3562902865" remote="-4611698899932405904" Dst="-1" /><file name="ys5bxjxHRU" server="60.43.193.157" local="3562902865" remote="-4611698899820345104" Dst="-1" /></dwsync>