<?xml version="1.0" encoding="utf-8" ?><dwsync><file name="ole-yl-a01.html" server="60.43.193.157" local="3562904084" remote="7704797296" Dst="-1" /><file name="ole-yl-a.html" server="60.43.193.157" local="3562904084" remote="7704797296" Dst="-1" /><file name="ole-yl-a02.html" server="60.43.193.157" local="3562904085" remote="-4611698899919445904" Dst="-1" /><file name="ole-yl-a03.html" server="60.43.193.157" local="3562904085" remote="-4611698899919445904" Dst="-1" /><file name="ole-yl-a04.html" server="60.43.193.157" local="3562904085" remote="-4611698899919445904" Dst="-1" /><file name="ole-yl-a06.html" server="60.43.193.157" local="3562904085" remote="-4611698899919445904" Dst="-1" /><file name="ole-yl-a05.html" server="60.43.193.157" local="3562904085" remote="-4611698899919445904" Dst="-1" /><file name="ole-yl-a07.html" server="60.43.193.157" local="3562904085" remote="-4611698899919445904" Dst="-1" /><file name="ole-yl-a08.html" server="60.43.193.157" local="3562904085" remote="-4611698899919445904" Dst="-1" /><file name="ole-yl-a09.html" server="60.43.193.157" local="3562904085" remote="-4611698899919445904" Dst="-1" /><file name="ole-yl-a10.html" server="60.43.193.157" local="3562904085" remote="-4611698899919445904" Dst="-1" /><file name="ole-yl-a11.html" server="60.43.193.157" local="3562904085" remote="-4611698899919445904" Dst="-1" /><file name="ole-yl-a12.html" server="60.43.193.157" local="3562904085" remote="-4611698899919445904" Dst="-1" /><file name="ole-yl-a13.html" server="60.43.193.157" local="3562904085" remote="-4611698899919445904" Dst="-1" /><file name="ole-yl-a14.html" server="60.43.193.157" local="3562904085" remote="-4611698899919445904" Dst="-1" /><file name="ole-yl-a15.html" server="60.43.193.157" local="3562904085" remote="-4611698899919445904" Dst="-1" /><file name="ole-yl-a16.html" server="60.43.193.157" local="3562904085" remote="-4611698899919445904" Dst="-1" /><file name="ole-yl-a17.html" server="60.43.193.157" local="3562904085" remote="-4611698899919445904" Dst="-1" /><file name="ole-yl-a_menu.html" server="60.43.193.157" local="3562904085" remote="-4611698899919445904" Dst="-1" /></dwsync>