<?xml version="1.0" encoding="utf-8" ?><dwsync><file name="2dbarcodes.php" server="60.43.193.157" local="3562904504" remote="7767350896" Dst="-1" /><file name="README.TXT" server="60.43.193.157" local="3562904504" remote="7767350896" Dst="-1" /><file name="LICENSE.TXT" server="60.43.193.157" local="3562904504" remote="-4611698899856892304" Dst="-1" /><file name="composer.json" server="60.43.193.157" local="3562904504" remote="-4611698899856892304" Dst="-1" /><file name="barcodes.php" server="60.43.193.157" local="3562904504" remote="7767350896" Dst="-1" /><file name="htmlcolors.php" server="60.43.193.157" local="3562904507" remote="7767350896" Dst="-1" /><file name="gpl.txt" server="60.43.193.157" local="3562904507" remote="-4611698899856892304" Dst="-1" /><file name="lgpl-3.0.txt" server="60.43.193.157" local="3562904507" remote="7767350896" Dst="-1" /><file name="pdf417.php" server="60.43.193.157" local="3562904508" remote="7767350896" Dst="-1" /><file name="qrcode.php" server="60.43.193.157" local="3562904508" remote="-4611698899856892304" Dst="-1" /><file name="tcpdf.crt" server="60.43.193.157" local="3562904508" remote="-4611698899856892304" Dst="-1" /><file name="tcpdf.fdf" server="60.43.193.157" local="3562904508" remote="-4611698899856892304" Dst="-1" /><file name="tcpdf.p12" server="60.43.193.157" local="3562904508" remote="-4611698899856892304" Dst="-1" /><file name="spotcolors.php" server="60.43.193.157" local="3562904508" remote="-4611698899856892304" Dst="-1" /><file name="tcpdf_autoconfig.php" server="60.43.193.157" local="3562904508" remote="-4611698899856892304" Dst="-1" /><file name="tcpdf_import.php" server="60.43.193.157" local="3562904508" remote="-4611698899856892304" Dst="-1" /><file name="tcpdf_parser.php" server="60.43.193.157" local="3562904508" remote="-4611698899856892304" Dst="-1" /><file name="unicode_data.php" server="60.43.193.157" local="3562904509" remote="7767350896" Dst="-1" /><file name="tcpdf.php" server="60.43.193.157" local="3562904509" remote="7767350896" Dst="-1" /></dwsync>