<?xml version="1.0" encoding="utf-8" ?><dwsync><file name="LEGALNOTICE" server="60.43.193.157" local="3562904337" remote="7767350896" Dst="-1" /><file name="README.md" server="60.43.193.157" local="3562904338" remote="-4611698899856892304" Dst="-1" /><file name="composer.json" server="60.43.193.157" local="3562904338" remote="-4611698899856892304" Dst="-1" /><file name="composer.lock" server="60.43.193.157" local="3562904338" remote="-4611698899856892304" Dst="-1" /><file name="console" server="60.43.193.157" local="3562904340" remote="7767350896" Dst="-1" /><file name="favicon.ico" server="60.43.193.157" local="3562904438" remote="7803898096" Dst="-1" /><file name="index.php" server="60.43.193.157" local="3562904438" remote="7767350896" Dst="-1" /><file name="piwik.js" server="60.43.193.157" local="3562904511" remote="7767350896" Dst="-1" /><file name="piwik.php" server="60.43.193.157" local="3562904511" remote="-4611698899856892304" Dst="-1" /><file name="robots.txt" server="60.43.193.157" local="3562904667" remote="7803898096" Dst="-1" /></dwsync>